torch_pme-0.4.0.dist-info/licenses/LICENSE
torchpme/__init__.py
torchpme/_utils.py
torchpme/_version.py
torchpme/prefactors.py
torchpme/calculators/__init__.py
torchpme/calculators/calculator.py
torchpme/calculators/calculator_dipole.py
torchpme/calculators/ewald.py
torchpme/calculators/p3m.py
torchpme/calculators/pme.py
torchpme/lib/__init__.py
torchpme/lib/kspace_filter.py
torchpme/lib/kvectors.py
torchpme/lib/math.py
torchpme/lib/mesh_interpolator.py
torchpme/lib/splines.py
torchpme/metatensor/__init__.py
torchpme/metatensor/calculator.py
torchpme/metatensor/ewald.py
torchpme/metatensor/p3m.py
torchpme/metatensor/pme.py
torchpme/potentials/__init__.py
torchpme/potentials/combined.py
torchpme/potentials/coulomb.py
torchpme/potentials/inversepowerlaw.py
torchpme/potentials/potential.py
torchpme/potentials/potential_dipole.py
torchpme/potentials/spline.py
torchpme/tuning/__init__.py
torchpme/tuning/ewald.py
torchpme/tuning/p3m.py
torchpme/tuning/pme.py
torchpme/tuning/tuner.py
torch_pme-0.4.0.dist-info/METADATA
torch_pme-0.4.0.dist-info/WHEEL
torch_pme-0.4.0.dist-info/top_level.txt
torch_pme-0.4.0.dist-info/RECORD
