Metadata-Version: 2.4
Name: torch-pme
Version: 0.4.0
Summary: Particle-mesh based calculations of long-range interactions in PyTorch
Author: torch-pme developers
License-Expression: BSD-3-Clause
Project-URL: homepage, https://lab-cosmo.github.io/torch-pme
Project-URL: documentation, https://lab-cosmo.github.io/torch-pme
Project-URL: repository, https://github.com/lab-cosmo/torch-pme
Project-URL: issues, https://github.com/lab-cosmo/torch-pme/issues
Project-URL: changelog, https://lab-cosmo.github.io/torch-pme/latest/references/changelog.html
Keywords: Auto-differentiation,Computational Materials Science,Electrostatics,Fourier Transform,GPU Acceleration,High-Performance Computing,Machine Learning,Molecular Dynamics,Particle-Mesh Ewald,PyTorch,Scientific Computing,TorchScript
Classifier: Development Status :: 4 - Beta
Classifier: Intended Audience :: Science/Research
Classifier: Natural Language :: English
Classifier: Operating System :: POSIX
Classifier: Operating System :: MacOS :: MacOS X
Classifier: Operating System :: Microsoft :: Windows
Classifier: Programming Language :: Python
Classifier: Programming Language :: Python :: 3
Classifier: Topic :: Scientific/Engineering
Classifier: Topic :: Scientific/Engineering :: Bio-Informatics
Classifier: Topic :: Scientific/Engineering :: Chemistry
Classifier: Topic :: Scientific/Engineering :: Physics
Classifier: Topic :: Software Development :: Libraries
Classifier: Topic :: Software Development :: Libraries :: Python Modules
Requires-Python: >=3.9
License-File: LICENSE
Requires-Dist: torch>=2.3
Provides-Extra: examples
Requires-Dist: ase>=3.22.1; extra == "examples"
Requires-Dist: chemiscope; extra == "examples"
Requires-Dist: matplotlib; extra == "examples"
Requires-Dist: metatensor-operations; extra == "examples"
Requires-Dist: scipy; extra == "examples"
Requires-Dist: vesin>=0.4.0; extra == "examples"
Requires-Dist: vesin-torch>=0.4.0; extra == "examples"
Provides-Extra: metatensor
Requires-Dist: metatensor-torch<0.9,>=0.7; extra == "metatensor"
Requires-Dist: metatomic-torch; extra == "metatensor"
Dynamic: license-file
